assemtools/__init__.py
assemtools/constant/__init__.py
assemtools/constant/dist_defs.py
assemtools/constant/installer_defs.py
assemtools/constant/linux/__init__.py
assemtools/constant/linux/app_admin.py
assemtools/constant/linux/app_systemd_daemon.py
assemtools/constant/win32/__init__.py
assemtools/constant/win32/winsvc.py
assemtools/core/__init__.py
assemtools/core/setup.py
assemtools/core/cmd/__init__.py
assemtools/core/cmd/bdist_app_command.py
assemtools/core/cmd/cleanup_command.py
assemtools/executable/__init__.py
assemtools/executable/dist.py
assemtools/executable/jupyter.py
assemtools/executable/run.py
assemtools/utility/__init__.py
assemtools/utility/os/__init__.py
assemtools/utility/os/os_utility.py
assemtools/utility/pkg/__init__.py
assemtools/utility/pkg/package_utility.py
assemtools/utility/string/__init__.py
assemtools/utility/string/string_utility.py
assemtools-0.0.1.dist-info/LICENSE
assemtools-0.0.1.dist-info/METADATA
assemtools-0.0.1.dist-info/WHEEL
assemtools-0.0.1.dist-info/top_level.txt
assemtools-0.0.1.dist-info/RECORD
